pkrfilesorter/__init__.py
pkrfilesorter/settings.py
pkrfilesorter/runs/__init__.py
pkrfilesorter/runs/cloud/__init__.py
pkrfilesorter/runs/cloud/correct_files.py
pkrfilesorter/runs/cloud/sort_files.py
pkrfilesorter/runs/cloud/sort_new_files.py
pkrfilesorter/runs/local/__init__.py
pkrfilesorter/runs/local/correct_files.py
pkrfilesorter/runs/local/sort_files.py
pkrfilesorter/runs/local/sort_new_files.py
pkrfilesorter/sorters/__init__.py
pkrfilesorter/sorters/abstract.py
pkrfilesorter/sorters/cloud.py
pkrfilesorter/sorters/local.py
pkrfilesorter-1.4.1.dist-info/LICENSE.txt
pkrfilesorter-1.4.1.dist-info/METADATA
pkrfilesorter-1.4.1.dist-info/WHEEL
pkrfilesorter-1.4.1.dist-info/top_level.txt
pkrfilesorter-1.4.1.dist-info/RECORD
