Metadata-Version: 2.1
Name: pkrfilesorter
Version: 1.4.1
Summary: A package to sort poker files in adapted directories
Home-page: https://github.com/manggy94/PokerFileSorter
Author: Alexandre MANGWA
Author-email: alex.mangwa@gmail.com
License: UNKNOWN
Project-URL: Bug Tracker, https://github.com/manggy94//issues
Project-URL: Documentation, https://pkrfilesorter.readthedocs.io/en/latest/
Platform: UNKNOWN
Classifier: Development Status :: 4 - Beta
Classifier: Intended Audience :: Developers
Classifier: License :: OSI Approved :: MIT License
Classifier: Natural Language :: English
Classifier: Programming Language :: Python
Classifier: Programming Language :: Python :: 3
Requires-Python: >=3.10
License-File: LICENSE.txt
Requires-Dist: python-dotenv
